{"version":1,"resource":"file:///home/arch/Documents/e-Commerce-Dart-Flutter/lib/View/login/login.dart","entries":[{"id":"AR4E.dart","timestamp":1713113913248},{"id":"x2np.dart","source":"undoRedo.source","timestamp":1713113916334},{"id":"RXCa.dart","timestamp":1713114091195},{"id":"iJtr.dart","timestamp":1713121828770},{"id":"Erbi.dart","timestamp":1713121854477},{"id":"tLRZ.dart","source":"undoRedo.source","timestamp":1713121861717},{"id":"MlIq.dart","timestamp":1713121871657},{"id":"2C2W.dart","timestamp":1713121885254},{"id":"qY1F.dart","timestamp":1713122015241},{"id":"PFmw.dart","timestamp":1713122028251},{"id":"X4Ty.dart","timestamp":1713122089728},{"id":"GkAD.dart","timestamp":1713122152268},{"id":"kBq5.dart","source":"Import library 'package:ecom_mobile/Model/open_database.dart'","timestamp":1713122167678},{"id":"r1VW.dart","timestamp":1713122194492},{"id":"XXla.dart","timestamp":1713122221292},{"id":"8Ih4.dart","timestamp":1713122447790},{"id":"sLid.dart","timestamp":1713122466907},{"id":"88zy.dart","source":"Import library 'package:ecom_mobile/objectbox.g.dart'","timestamp":1713122587068},{"id":"ZKmr.dart","timestamp":1713122608408},{"id":"yPEY.dart","timestamp":1713122646575},{"id":"dWIm.dart","timestamp":1713122679612},{"id":"JFmE.dart","timestamp":1713122691172},{"id":"egvo.dart","timestamp":1713122712692},{"id":"Y8ax.dart","timestamp":1713122800596},{"id":"C8b6.dart","timestamp":1713122846556},{"id":"9gsu.dart","timestamp":1713122881630},{"id":"jCka.dart","timestamp":1713122935750},{"id":"XjMj.dart","timestamp":1713122958721},{"id":"RvQs.dart","timestamp":1713122973447},{"id":"96OF.dart","timestamp":1713123072951},{"id":"S3Ru.dart","timestamp":1713123117368},{"id":"Fvkh.dart","timestamp":1713123297590},{"id":"3TJN.dart","timestamp":1713123414081},{"id":"DkTP.dart","source":"undoRedo.source","timestamp":1713123422221},{"id":"5RsH.dart","timestamp":1713123453394},{"id":"rTTK.dart","timestamp":1713123482891},{"id":"CspW.dart","timestamp":1713123500981},{"id":"FK7V.dart","timestamp":1713123569619},{"id":"EWPm.dart","timestamp":1713123581592},{"id":"MOWm.dart","timestamp":1713123601482},{"id":"ffSS.dart","timestamp":1713123634133},{"id":"yxkD.dart","timestamp":1713123684456},{"id":"DLJ5.dart","timestamp":1713123795951},{"id":"f873.dart","timestamp":1713125099643},{"id":"rKsT.dart","timestamp":1713130946046}]}